gozero_signature.py
gozero_signature_python-0.1.0.dist-info/METADATA
gozero_signature_python-0.1.0.dist-info/WHEEL
gozero_signature_python-0.1.0.dist-info/top_level.txt
gozero_signature_python-0.1.0.dist-info/RECORD
