Metadata-Version: 2.4
Name: gozero-signature-python
Version: 0.1.0
Summary: Python implementation of go-zero framework signature functionality
Author: Your Name
Author-email: your.email@example.com
Keywords: go-zero,security,signature,encryption
Requires-Python: >=3.6
Requires-Dist: pycryptodome>=3.15.0
Dynamic: author
Dynamic: author-email
Dynamic: keywords
Dynamic: requires-dist
Dynamic: requires-python
Dynamic: summary
